<Properties StartupConfiguration="{B7E038DC-4685-4664-8234-6EACAA9E69DF}|Default">
  <MonoDevelop.Ide.Workbench ActiveDocument="ESBCommunitySite/Controllers/InfoController.cs">
    <Files>
      <File FileName="ESBCommunitySite/Controllers/InfoController.cs" Line="21" Column="60" />
      <File FileName="ESBCommunitySite/Views/Home/Index.cshtml" Line="11" Column="11" />
      <File FileName="ESBCommunitySite/Controllers/HomeController.cs" Line="21" Column="28" />
    </Files>
    <Pads>
      <Pad Id="ProjectPad">
        <State name="__root__">
          <Node name="ESBCommunitySite" expanded="True">
            <Node name="ESBCommunitySite" expanded="True">
              <Node name="Dependencies" expanded="True">
                <Node name="PackageDependencies" expanded="True" />
              </Node>
              <Node name="Controllers" expanded="True">
                <Node name="InfoController.cs" selected="True" />
              </Node>
              <Node name="Models" expanded="True" />
              <Node name="Properties" expanded="True" />
              <Node name="Views" expanded="True">
                <Node name="Home" expanded="True" />
                <Node name="Info" expanded="True" />
                <Node name="Shared" expanded="True" />
              </Node>
              <Node name="wwwroot" expanded="True" />
            </Node>
          </Node>
        </State>
      </Pad>
    </Pads>
  </MonoDevelop.Ide.Workbench>
  <MonoDevelop.Ide.ItemProperties.ESBCommunitySite PreferredExecutionTarget="/Applications/Firefox Nightly.app" />
  <MonoDevelop.Ide.DebuggingService.PinnedWatches />
  <MonoDevelop.Ide.Workspace ActiveConfiguration="Debug" />
  <MonoDevelop.Ide.DebuggingService.Breakpoints>
    <BreakpointStore>
      <Breakpoint file="/usr/local/share/dotnet/sdk/3.0.100/Sdks/Microsoft.NET.Sdk/targets/Microsoft.NET.Sdk.DefaultItems.targets" line="187" column="65" />
    </BreakpointStore>
  </MonoDevelop.Ide.DebuggingService.Breakpoints>
  <MultiItemStartupConfigurations />
</Properties>